{"id":"4ada51a5-0d9a-4493-92f3-e2561543fc42","index":2548,"period":2,"timestamp":"00:17:25.696","minute":62,"second":25,"type":{"id":30,"name":"Pass"},"possession":120,"possession_team":{"id":217,"name":"Barcelona"},"play_pattern":{"id":1,"name":"Regular Play"},"team":{"id":217,"name":"Barcelona"},"duration":0.507885,"tactics":null,"related_events":["75d6d3d3-2a0b-4664-8312-a1ad0be1db22"],"player":{"id":10609,"name":"J\u00e9r\u00e9my Mathieu"},"position":{"id":5,"name":"Left Center Back"},"location":[58.2,42.7],"pass":{"recipient":{"id":5203,"name":"Sergio Busquets i Burgos"},"length":6.963476,"angle":0.21711132,"height":{"id":1,"name":"Ground Pass"},"end_location":[65.0,44.2],"body_part":{"id":38,"name":"Left Foot"}},"carry":null,"under_pressure":null,"ball_receipt":null,"out":null,"clearance":null,"counterpress":null,"duel":null,"off_camera":null,"dribble":null,"miscontrol":null,"interception":null,"shot":null,"goalkeeper":null,"block":null,"foul_committed":null,"substitution":null,"foul_won":null,"ball_recovery":null}
{"id":"db2a3ab6-ef75-4eed-a76c-c8dd97f26f6e","index":2551,"period":2,"timestamp":"00:17:26.324","minute":62,"second":26,"type":{"id":30,"name":"Pass"},"possession":120,"possession_team":{"id":217,"name":"Barcelona"},"play_pattern":{"id":1,"name":"Regular Play"},"team":{"id":217,"name":"Barcelona"},"duration":1.237305,"tactics":null,"related_events":["31300f43-7f84-4150-9aea-7a0c9657b898"],"player":{"id":5203,"name":"Sergio Busquets i Burgos"},"position":{"id":10,"name":"Center Defensive Midfield"},"location":[64.9,44.7],"pass":{"recipient":{"id":5506,"name":"Javier Alejandro Mascherano"},"length":16.484236,"angle":2.8524601,"height":{"id":1,"name":"Ground Pass"},"end_location":[49.1,49.4],"body_part":{"id":40,"name":"Right Foot"}},"carry":null,"under_pressure":null,"ball_receipt":null,"out":null,"clearance":null,"counterpress":null,"duel":null,"off_camera":null,"dribble":null,"miscontrol":null,"interception":null,"shot":null,"goalkeeper":null,"block":null,"foul_committed":null,"substitution":null,"foul_won":null,"ball_recovery":null}
{"id":"60140725-b72e-4874-9546-136121df1e33","index":2554,"period":2,"timestamp":"00:17:28.617","minute":62,"second":28,"type":{"id":30,"name":"Pass"},"possession":120,"possession_team":{"id":217,"name":"Barcelona"},"play_pattern":{"id":1,"name":"Regular Play"},"team":{"id":217,"name":"Barcelona"},"duration":1.337445,"tactics":null,"related_events":["e9477449-dc74-441d-9ee7-525c4fa633d4"],"player":{"id":5506,"name":"Javier Alejandro Mascherano"},"position":{"id":3,"name":"Right Center Back"},"location":[49.9,47.5],"pass":{"recipient":{"id":5203,"name":"Sergio Busquets i Burgos"},"length":10.301942,"angle":-0.019415036,"height":{"id":1,"name":"Ground Pass"},"end_location":[60.2,47.3],"body_part":{"id":40,"name":"Right Foot"}},"carry":null,"under_pressure":null,"ball_receipt":null,"out":null,"clearance":null,"counterpress":null,"duel":null,"off_camera":null,"dribble":null,"miscontrol":null,"interception":null,"shot":null,"goalkeeper":null,"block":null,"foul_committed":null,"substitution":null,"foul_won":null,"ball_recovery":null}
{"id":"678b3f20-8f2f-4aec-9e95-1888aeaa1a91","index":2557,"period":2,"timestamp":"00:17:30.885","minute":62,"second":30,"type":{"id":30,"name":"Pass"},"possession":120,"possession_team":{"id":217,"name":"Barcelona"},"play_pattern":{"id":1,"name":"Regular Play"},"team":{"id":217,"name":"Barcelona"},"duration":0.747699,"tactics":null,"related_events":["5ba0723d-bb26-4b86-a424-7d1929d340fd"],"player":{"id":5203,"name":"Sergio Busquets i Burgos"},"position":{"id":10,"name":"Center Defensive Midfield"},"location":[61.2,49.0],"pass":{"recipient":{"id":5503,"name":"Lionel Andr\u00e9s Messi Cuccittini"},"length":8.188406,"angle":-0.49642277,"height":{"id":1,"name":"Ground Pass"},"end_location":[68.4,45.1],"body_part":{"id":40,"name":"Right Foot"}},"carry":null,"under_pressure":null,"ball_receipt":null,"out":null,"clearance":null,"counterpress":null,"duel":null,"off_camera":null,"dribble":null,"miscontrol":null,"interception":null,"shot":null,"goalkeeper":null,"block":null,"foul_committed":null,"substitution":null,"foul_won":null,"ball_recovery":null}
{"id":"3e554982-930b-4828-858c-80281e705b71","index":2578,"period":2,"timestamp":"00:18:03.570","minute":63,"second":3,"type":{"id":30,"name":"Pass"},"possession":123,"possession_team":{"id":217,"name":"Barcelona"},"play_pattern":{"id":1,"name":"Regular Play"},"team":{"id":217,"name":"Barcelona"},"duration":1.069363,"tactics":null,"related_events":["3454b495-6025-45dc-b3d4-156b51ff9d2c","4bae87e7-3470-4591-8a36-5eec83695581"],"player":{"id":5503,"name":"Lionel Andr\u00e9s Messi Cuccittini"},"position":{"id":23,"name":"Center Forward"},"location":[88.9,72.5],"pass":{"recipient":{"id":6379,"name":"Sergi Roberto Carnicer"},"length":6.530697,"angle":-2.0138988,"height":{"id":2,"name":"Low Pass"},"end_location":[86.1,66.6],"aerial_won":true,"type":{"id":66,"name":"Recovery"}},"carry":null,"under_pressure":true,"ball_receipt":null,"out":null,"clearance":null,"counterpress":null,"duel":null,"off_camera":null,"dribble":null,"miscontrol":null,"interception":null,"shot":null,"goalkeeper":null,"block":null,"foul_committed":null,"substitution":null,"foul_won":null,"ball_recovery":null}
{"id":"87148201-9114-4640-9748-34aa88975bec","index":2581,"period":2,"timestamp":"00:18:05.845","minute":63,"second":5,"type":{"id":30,"name":"Pass"},"possession":123,"possession_team":{"id":217,"name":"Barcelona"},"play_pattern":{"id":1,"name":"Regular Play"},"team":{"id":217,"name":"Barcelona"},"duration":0.763494,"tactics":null,"related_events":["5d6f6e91-4f76-4d90-9fb6-5596636c79f9"],"player":{"id":6379,"name":"Sergi Roberto Carnicer"},"position":{"id":15,"name":"Left Center Midfield"},"location":[89.9,63.5],"pass":{"recipient":{"id":4320,"name":"Neymar da Silva Santos Junior"},"length":14.112761,"angle":-1.5282688,"height":{"id":1,"name":"Ground Pass"},"end_location":[90.5,49.4],"body_part":{"id":40,"name":"Right Foot"}},"carry":null,"under_pressure":null,"ball_receipt":null,"out":null,"clearance":null,"counterpress":null,"duel":null,"off_camera":null,"dribble":null,"miscontrol":null,"interception":null,"shot":null,"goalkeeper":null,"block":null,"foul_committed":null,"substitution":null,"foul_won":null,"ball_recovery":null}
{"id":"02c53702-2075-4639-a6ce-e0ebadd9e3a0","index":2584,"period":2,"timestamp":"00:18:06.769","minute":63,"second":6,"type":{"id":30,"name":"Pass"},"possession":123,"possession_team":{"id":217,"name":"Barcelona"},"play_pattern":{"id":1,"name":"Regular Play"},"team":{"id":217,"name":"Barcelona"},"duration":0.8756,"tactics":null,"related_events":["81d4cbd3-180c-48b7-a685-323856a13adb"],"player":{"id":4320,"name":"Neymar da Silva Santos Junior"},"position":{"id":21,"name":"Left Wing"},"location":[90.8,49.3],"pass":{"recipient":{"id":6379,"name":"Sergi Roberto Carnicer"},"length":9.972462,"angle":0.80667156,"height":{"id":2,"name":"Low Pass"},"end_location":[97.7,56.5],"body_part":{"id":40,"name":"Right Foot"}},"carry":null,"under_pressure":null,"ball_receipt":null,"out":null,"clearance":null,"counterpress":null,"duel":null,"off_camera":null,"dribble":null,"miscontrol":null,"interception":null,"shot":null,"goalkeeper":null,"block":null,"foul_committed":null,"substitution":null,"foul_won":null,"ball_recovery":null}
{"id":"5e8c73c2-ebb4-482b-ba78-408b51f8a906","index":2640,"period":2,"timestamp":"00:19:46.208","minute":64,"second":46,"type":{"id":30,"name":"Pass"},"possession":126,"possession_team":{"id":217,"name":"Barcelona"},"play_pattern":{"id":3,"name":"From Free Kick"},"team":{"id":217,"name":"Barcelona"},"duration":2.998476,"tactics":null,"related_events":["77a5c2dc-a308-484c-98e5-a3afb2f0b0b2"],"player":{"id":4691,"name":"Claudio Andr\u00e9s Bravo Mu\u00f1oz"},"position":{"id":1,"name":"Goalkeeper"},"location":[44.0,12.8],"pass":{"recipient":{"id":4320,"name":"Neymar da Silva Santos Junior"},"length":52.171352,"angle":0.49536937,"height":{"id":3,"name":"High Pass"},"end_location":[89.9,37.6],"type":{"id":62,"name":"Free Kick"},"body_part":{"id":38,"name":"Left Foot"}},"carry":null,"under_pressure":null,"ball_receipt":null,"out":null,"clearance":null,"counterpress":null,"duel":null,"off_camera":true,"dribble":null,"miscontrol":null,"interception":null,"shot":null,"goalkeeper":null,"block":null,"foul_committed":null,"substitution":null,"foul_won":null,"ball_recovery":null}
{"id":"0613b266-3911-4c8b-9a23-b7af5637aea2","index":2642,"period":2,"timestamp":"00:19:49.517","minute":64,"second":49,"type":{"id":30,"name":"Pass"},"possession":126,"possession_team":{"id":217,"name":"Barcelona"},"play_pattern":{"id":3,"name":"From Free Kick"},"team":{"id":217,"name":"Barcelona"},"duration":0.904022,"tactics":null,"related_events":["740c885b-76b8-4120-8f9e-9e91fecd777b"],"player":{"id":4320,"name":"Neymar da Silva Santos Junior"},"position":{"id":21,"name":"Left Wing"},"location":[84.3,37.6],"pass":{"recipient":{"id":6379,"name":"Sergi Roberto Carnicer"},"length":2.236068,"angle":2.0344439,"height":{"id":2,"name":"Low Pass"},"end_location":[83.3,39.6],"body_part":{"id":37,"name":"Head"}},"carry":null,"under_pressure":null,"ball_receipt":null,"out":null,"clearance":null,"counterpress":null,"duel":null,"off_camera":true,"dribble":null,"miscontrol":null,"interception":null,"shot":null,"goalkeeper":null,"block":null,"foul_committed":null,"substitution":null,"foul_won":null,"ball_recovery":null}
{"id":"bc4625bf-91c5-4543-bae4-b548a0990ffc","index":2646,"period":2,"timestamp":"00:19:50.461","minute":64,"second":50,"type":{"id":30,"name":"Pass"},"possession":126,"possession_team":{"id":217,"name":"Barcelona"},"play_pattern":{"id":3,"name":"From Free Kick"},"team":{"id":217,"name":"Barcelona"},"duration":0.766159,"tactics":null,"related_events":["17afbc75-7679-40e4-afbe-963937440007","6d292e1a-2027-4149-ad6e-b74ab0517ae9"],"player":{"id":6379,"name":"Sergi Roberto Carnicer"},"position":{"id":15,"name":"Left Center Midfield"},"location":[83.2,37.9],"pass":{"recipient":{"id":5506,"name":"Javier Alejandro Mascherano"},"length":12.603571,"angle":3.1177876,"height":{"id":2,"name":"Low Pass"},"end_location":[70.6,38.2],"body_part":{"id":40,"name":"Right Foot"}},"carry":null,"under_pressure":true,"ball_receipt":null,"out":null,"clearance":null,"counterpress":null,"duel":null,"off_camera":null,"dribble":null,"miscontrol":null,"interception":null,"shot":null,"goalkeeper":null,"block":null,"foul_committed":null,"substitution":null,"foul_won":null,"ball_recovery":null}
{"id":"37d87cb2-97e6-423f-af41-d2ae335420e0","index":2649,"period":2,"timestamp":"00:19:51.446","minute":64,"second":51,"type":{"id":30,"name":"Pass"},"possession":126,"possession_team":{"id":217,"name":"Barcelona"},"play_pattern":{"id":3,"name":"From Free Kick"},"team":{"id":217,"name":"Barcelona"},"duration":1.036622,"tactics":null,"related_events":["6056aae3-2efb-4c7f-acd5-c2688c35ce73"],"player":{"id":5506,"name":"Javier Alejandro Mascherano"},"position":{"id":3,"name":"Right Center Back"},"location":[70.6,38.2],"pass":{"recipient":{"id":20131,"name":"Xavier Hern\u00e1ndez Creus"},"length":17.88463,"angle":-1.1747149,"height":{"id":2,"name":"Low Pass"},"end_location":[77.5,21.7],"body_part":{"id":40,"name":"Right Foot"}},"carry":null,"under_pressure":null,"ball_receipt":null,"out":null,"clearance":null,"counterpress":null,"duel":null,"off_camera":null,"dribble":null,"miscontrol":null,"interception":null,"shot":null,"goalkeeper":null,"block":null,"foul_committed":null,"substitution":null,"foul_won":null,"ball_recovery":null}
{"id":"f2ca12bf-e1c6-4cb3-b0b0-8901a8c26f36","index":2652,"period":2,"timestamp":"00:19:55.143","minute":64,"second":55,"type":{"id":30,"name":"Pass"},"possession":126,"possession_team":{"id":217,"name":"Barcelona"},"play_pattern":{"id":3,"name":"From Free Kick"},"team":{"id":217,"name":"Barcelona"},"duration":2.818033,"tactics":null,"related_events":["6b4607f3-37e1-4147-8b05-15414a87f52f"],"player":{"id":20131,"name":"Xavier Hern\u00e1ndez Creus"},"position":{"id":13,"name":"Right Center Midfield"},"location":[80.4,23.0],"pass":{"recipient":{"id":4324,"name":"Daniel Alves da Silva"},"length":57.670963,"angle":1.3523154,"height":{"id":3,"name":"High Pass"},"end_location":[92.9,79.3],"switch":true,"body_part":{"id":40,"name":"Right Foot"}},"carry":null,"under_pressure":null,"ball_receipt":null,"out":null,"clearance":null,"counterpress":null,"duel":null,"off_camera":null,"dribble":null,"miscontrol":null,"interception":null,"shot":null,"goalkeeper":null,"block":null,"foul_committed":null,"substitution":null,"foul_won":null,"ball_recovery":null}
{"id":"f56250a8-5931-4688-8c00-9c963ee841f1","index":2655,"period":2,"timestamp":"00:19:58.910","minute":64,"second":58,"type":{"id":30,"name":"Pass"},"possession":126,"possession_team":{"id":217,"name":"Barcelona"},"play_pattern":{"id":3,"name":"From Free Kick"},"team":{"id":217,"name":"Barcelona"},"duration":0.946034,"tactics":null,"related_events":["8f8afbef-1ca6-440a-ba8b-b0b17052667d"],"player":{"id":4324,"name":"Daniel Alves da Silva"},"position":{"id":2,"name":"Right Back"},"location":[92.3,73.1],"pass":{"recipient":{"id":6616,"name":"Munir El Haddadi Mohamed"},"length":9.402127,"angle":-2.082027,"height":{"id":1,"name":"Ground Pass"},"end_location":[87.7,64.9],"body_part":{"id":40,"name":"Right Foot"}},"carry":null,"under_pressure":null,"ball_receipt":null,"out":null,"clearance":null,"counterpress":null,"duel":null,"off_camera":null,"dribble":null,"miscontrol":null,"interception":null,"shot":null,"goalkeeper":null,"block":null,"foul_committed":null,"substitution":null,"foul_won":null,"ball_recovery":null}
{"id":"af3c3c7a-cb05-4b4b-9a08-ad1cb04a0cb6","index":2658,"period":2,"timestamp":"00:20:01.157","minute":65,"second":1,"type":{"id":30,"name":"Pass"},"possession":126,"possession_team":{"id":217,"name":"Barcelona"},"play_pattern":{"id":3,"name":"From Free Kick"},"team":{"id":217,"name":"Barcelona"},"duration":1.242281,"tactics":null,"related_events":["035fe6fa-a3dc-44b6-99c9-3c10d6dba805"],"player":{"id":6616,"name":"Munir El Haddadi Mohamed"},"position":{"id":17,"name":"Right Wing"},"location":[85.3,62.7],"pass":{"recipient":{"id":5506,"name":"Javier Alejandro Mascherano"},"length":15.5128975,"angle":-2.2969034,"height":{"id":1,"name":"Ground Pass"},"end_location":[75.0,51.1],"body_part":{"id":38,"name":"Left Foot"}},"carry":null,"under_pressure":null,"ball_receipt":null,"out":null,"clearance":null,"counterpress":null,"duel":null,"off_camera":null,"dribble":null,"miscontrol":null,"interception":null,"shot":null,"goalkeeper":null,"block":null,"foul_committed":null,"substitution":null,"foul_won":null,"ball_recovery":null}
{"id":"ef0312fe-30cc-43b1-8dc4-9dd582c4fb0a","index":2661,"period":2,"timestamp":"00:20:04.088","minute":65,"second":4,"type":{"id":30,"name":"Pass"},"possession":126,"possession_team":{"id":217,"name":"Barcelona"},"play_pattern":{"id":3,"name":"From Free Kick"},"team":{"id":217,"name":"Barcelona"},"duration":2.99079,"tactics":null,"related_events":["dabf9389-c8b6-4527-90be-3ec58172442c"],"player":{"id":5506,"name":"Javier Alejandro Mascherano"},"position":{"id":3,"name":"Right Center Back"},"location":[78.4,50.8],"pass":{"recipient":{"id":22102,"name":"Adriano Correia Claro"},"length":51.400875,"angle":-1.0200335,"height":{"id":3,"name":"High Pass"},"end_location":[105.3,7.0],"switch":true,"body_part":{"id":40,"name":"Right Foot"}},"carry":null,"under_pressure":null,"ball_receipt":null,"out":null,"clearance":null,"counterpress":null,"duel":null,"off_camera":null,"dribble":null,"miscontrol":null,"interception":null,"shot":null,"goalkeeper":null,"block":null,"foul_committed":null,"substitution":null,"foul_won":null,"ball_recovery":null}
{"id":"81b7b5aa-0e93-47f3-9135-9d6e5eebcc2f","index":2664,"period":2,"timestamp":"00:20:08.619","minute":65,"second":8,"type":{"id":30,"name":"Pass"},"possession":126,"possession_team":{"id":217,"name":"Barcelona"},"play_pattern":{"id":3,"name":"From Free Kick"},"team":{"id":217,"name":"Barcelona"},"duration":1.611248,"tactics":null,"related_events":["e9f49a39-0301-4b7b-ac93-987d9d9118bd"],"player":{"id":22102,"name":"Adriano Correia Claro"},"position":{"id":6,"name":"Left Back"},"location":[100.6,5.5],"pass":{"recipient":{"id":20131,"name":"Xavier Hern\u00e1ndez Creus"},"length":22.83725,"angle":1.914704,"height":{"id":2,"name":"Low Pass"},"end_location":[92.9,27.0],"body_part":{"id":40,"name":"Right Foot"}},"carry":null,"under_pressure":null,"ball_receipt":null,"out":null,"clearance":null,"counterpress":null,"duel":null,"off_camera":null,"dribble":null,"miscontrol":null,"interception":null,"shot":null,"goalkeeper":null,"block":null,"foul_committed":null,"substitution":null,"foul_won":null,"ball_recovery":null}
{"id":"43268150-91fe-47c2-98ce-c219bf4cc613","index":2667,"period":2,"timestamp":"00:20:10.872","minute":65,"second":10,"type":{"id":30,"name":"Pass"},"possession":126,"possession_team":{"id":217,"name":"Barcelona"},"play_pattern":{"id":3,"name":"From Free Kick"},"team":{"id":217,"name":"Barcelona"},"duration":0.77411,"tactics":null,"related_events":["8dad8fa6-87a1-4698-8d0d-420996f32bb5"],"player":{"id":20131,"name":"Xavier Hern\u00e1ndez Creus"},"position":{"id":13,"name":"Right Center Midfield"},"location":[97.5,28.6],"pass":{"recipient":{"id":5503,"name":"Lionel Andr\u00e9s Messi Cuccittini"},"length":12.880994,"angle":-0.4497596,"height":{"id":1,"name":"Ground Pass"},"end_location":[109.1,23.0],"body_part":{"id":40,"name":"Right Foot"}},"carry":null,"under_pressure":null,"ball_receipt":null,"out":null,"clearance":null,"counterpress":null,"duel":null,"off_camera":null,"dribble":null,"miscontrol":null,"interception":null,"shot":null,"goalkeeper":null,"block":null,"foul_committed":null,"substitution":null,"foul_won":null,"ball_recovery":null}
{"id":"8e57ec3e-f73d-42b1-9a3a-39012764dec5","index":2670,"period":2,"timestamp":"00:20:12.341","minute":65,"second":12,"type":{"id":30,"name":"Pass"},"possession":126,"possession_team":{"id":217,"name":"Barcelona"},"play_pattern":{"id":3,"name":"From Free Kick"},"team":{"id":217,"name":"Barcelona"},"duration":1.010284,"tactics":null,"related_events":["f384e844-1d77-4fdc-80a7-8f90245c5b29"],"player":{"id":5503,"name":"Lionel Andr\u00e9s Messi Cuccittini"},"position":{"id":23,"name":"Center Forward"},"location":[113.2,25.4],"pass":{"recipient":{"id":4320,"name":"Neymar da Silva Santos Junior"},"length":12.083874,"angle":1.7454685,"height":{"id":1,"name":"Ground Pass"},"end_location":[111.1,37.3],"cross":true,"assisted_shot_id":"d5c9e5da-fcb0-4c10-8f41-d03e3e7a9c41","goal_assist":true,"body_part":{"id":38,"name":"Left Foot"}},"carry":null,"under_pressure":null,"ball_receipt":null,"out":null,"clearance":null,"counterpress":null,"duel":null,"off_camera":null,"dribble":null,"miscontrol":null,"interception":null,"shot":null,"goalkeeper":null,"block":null,"foul_committed":null,"substitution":null,"foul_won":null,"ball_recovery":null}
